README.md
setup.py
./prominence/__init__.py
./prominence/auth.py
./prominence/client.py
./prominence/exceptions.py
bin/prominence
prominence_cli.egg-info/PKG-INFO
prominence_cli.egg-info/SOURCES.txt
prominence_cli.egg-info/dependency_links.txt
prominence_cli.egg-info/requires.txt
prominence_cli.egg-info/top_level.txt