Metadata-Version: 2.1
Name: prominence-cli
Version: 1.1.0
Summary: PROMINENCE CLI for managing batch jobs running across clouds
Home-page: https://prominence.readthedocs.io
Author: Andrew Lahiff
Author-email: andrew.lahiff@ukaea.uk
License: UNKNOWN
Platform: any
